AUTHORS
MANIFEST.in
README.md
setup.py
Django_WYSIWYG_Forms.egg-info/PKG-INFO
Django_WYSIWYG_Forms.egg-info/SOURCES.txt
Django_WYSIWYG_Forms.egg-info/dependency_links.txt
Django_WYSIWYG_Forms.egg-info/requires.txt
Django_WYSIWYG_Forms.egg-info/top_level.txt
django_wysiwyg_forms.egg-info/SOURCES.txt
wysiwyg_forms/__init__.py
wysiwyg_forms/admin.py
wysiwyg_forms/exceptions.py
wysiwyg_forms/models.py
wysiwyg_forms/tests.py
wysiwyg_forms/transactions.py
wysiwyg_forms/urls.py
wysiwyg_forms/utils.py
wysiwyg_forms/views.py
wysiwyg_forms/static/wysiwyg_forms/css/dwf.css
wysiwyg_forms/static/wysiwyg_forms/js/dwf.js
wysiwyg_forms/static/wysiwyg_forms/js/dwf.min.js
wysiwyg_forms/static/wysiwyg_forms/js/jquery-ui.js
wysiwyg_forms/static/wysiwyg_forms/js/jquery.django-csrf.js
wysiwyg_forms/static/wysiwyg_forms/js/require.js
wysiwyg_forms/static/wysiwyg_forms/js/test.js
wysiwyg_forms/static/wysiwyg_forms/js/text.js
wysiwyg_forms/static/wysiwyg_forms/js/dwf/field-types.js
wysiwyg_forms/static/wysiwyg_forms/js/dwf/transactions.js
wysiwyg_forms/static/wysiwyg_forms/js/dwf/util.js
wysiwyg_forms/static/wysiwyg_forms/js/dwf/widgets.js
wysiwyg_forms/static/wysiwyg_forms/js/dwf/models/choice.js
wysiwyg_forms/static/wysiwyg_forms/js/dwf/models/field.js
wysiwyg_forms/static/wysiwyg_forms/js/dwf/models/form.js
wysiwyg_forms/static/wysiwyg_forms/js/dwf/views/add-field-tab.html
wysiwyg_forms/static/wysiwyg_forms/js/dwf/views/add-field-tab.js
wysiwyg_forms/static/wysiwyg_forms/js/dwf/views/base-view.js
wysiwyg_forms/static/wysiwyg_forms/js/dwf/views/control-panel.html
wysiwyg_forms/static/wysiwyg_forms/js/dwf/views/control-panel.js
wysiwyg_forms/static/wysiwyg_forms/js/dwf/views/field-preview.html
wysiwyg_forms/static/wysiwyg_forms/js/dwf/views/field-preview.js
wysiwyg_forms/static/wysiwyg_forms/js/dwf/views/field-settings-tab.html
wysiwyg_forms/static/wysiwyg_forms/js/dwf/views/field-settings-tab.js
wysiwyg_forms/static/wysiwyg_forms/js/dwf/views/form-preview.html
wysiwyg_forms/static/wysiwyg_forms/js/dwf/views/form-preview.js
wysiwyg_forms/static/wysiwyg_forms/js/dwf/views/form-settings-tab.html
wysiwyg_forms/static/wysiwyg_forms/js/dwf/views/form-settings-tab.js
wysiwyg_forms/static/wysiwyg_forms/js/dwf/views/messages.html
