Metadata-Version: 1.0
Name: django-wysiwyg-forms
Version: 0.1.1
Summary: A What You See Is What You Get form editor for Django.
Home-page: https://github.com/fitzgen/django-wysiwyg-forms
Author: Nick Fitzgerald
Author-email: fitzgen@gmail.com
License: UNKNOWN
Platform: UNKNOWN
